README.rst
setup.cfg
setup.py
bloodyterminal/__init__.py
bloodyterminal.egg-info/PKG-INFO
bloodyterminal.egg-info/SOURCES.txt
bloodyterminal.egg-info/dependency_links.txt
bloodyterminal.egg-info/requires.txt
bloodyterminal.egg-info/top_level.txt