Metadata-Version: 1.1
Name: bloodyterminal
Version: 4.0
Summary: A little helper to structure your terminal output
Home-page: https://github.com/TheBloodyScreen/bloodyterminal/
Author: TheBloodyScreen
Author-email: jaydee@thebloodyscreen.com
License: MIT
Platform: UNKNOWN
Classifier: Development Status :: 3 - Alpha
Classifier: Intended Audience :: Developers
Classifier: License :: OSI Approved :: MIT License
Classifier: Programming Language :: Python :: 3.6
